xhs_mcp_server/__init__.py
xhs_mcp_server/__login__.py
xhs_mcp_server/__main__.py
xhs_mcp_server/server.py
xhs_mcp_server/write_xiaohongshu.py
xhs_mcp_server/test/create_note.py
xhs_mcp_server/test/login_publish.py
xhs_mcp_server/test/login_publish_video.py
xhs_mcp_server-0.2.8.dist-info/METADATA
xhs_mcp_server-0.2.8.dist-info/WHEEL
xhs_mcp_server-0.2.8.dist-info/entry_points.txt
xhs_mcp_server-0.2.8.dist-info/RECORD
