Metadata-Version: 2.4
Name: xhs_mcp_server
Version: 0.2.8
Summary: A Model Context Protocol (MCP) server to post xiaohongshu(rednote,小红书)
Author-email: Zhiling Luo <godot.lzl@alibaba-inc.com>
Requires-Python: >=3.11
Requires-Dist: mcp>=1.0.0
Requires-Dist: requests
Requires-Dist: selenium
